zope/app/broken/__init__.py
zope/app/broken/broken.gif
zope/app/broken/broken.pt
zope/app/broken/broken.py
zope/app/broken/browser.zcml
zope/app/broken/configure.zcml
zope/app/broken/tests.py
zope_app_broken-6.0.dist-info/licenses/LICENSE.txt
zope_app_broken-6.0.dist-info/METADATA
zope_app_broken-6.0.dist-info/WHEEL
zope_app_broken-6.0.dist-info/top_level.txt
zope_app_broken-6.0.dist-info/RECORD
