Metadata-Version: 2.4
Name: zope.app.broken
Version: 6.0
Summary: Zope Broken (ZODB) Object Support
Home-page: http://github.com/zopefoundation/zope.app.broken
Author: Zope Foundation and Contributors
Author-email: zope-dev@zope.dev
License: ZPL-2.1
Keywords: zope3 content provider
Classifier: Development Status :: 5 - Production/Stable
Classifier: Environment :: Web Environment
Classifier: Framework :: Zope :: 3
Classifier: Intended Audience :: Developers
Classifier: License :: OSI Approved :: Zope Public License
Classifier: Natural Language :: English
Classifier: Operating System :: OS Independent
Classifier: Programming Language :: Python :: 3
Classifier: Programming Language :: Python :: 3.9
Classifier: Programming Language :: Python :: 3.10
Classifier: Programming Language :: Python :: 3.11
Classifier: Programming Language :: Python :: 3.12
Classifier: Programming Language :: Python :: 3.13
Classifier: Programming Language :: Python :: Implementation :: CPython
Classifier: Programming Language :: Python :: Implementation :: PyPy
Classifier: Programming Language :: Python
Classifier: Topic :: Internet :: WWW/HTTP
Requires-Python: >=3.9
License-File: LICENSE.txt
Requires-Dist: setuptools
Requires-Dist: zope.deferredimport
Requires-Dist: zope.interface
Requires-Dist: zope.location
Requires-Dist: zope.security
Requires-Dist: zope.annotation
Requires-Dist: zope.processlifetime
Requires-Dist: ZODB>=3.10.0a1
Provides-Extra: test
Requires-Dist: zope.browsermenu; extra == "test"
Requires-Dist: zope.browserpage; extra == "test"
Requires-Dist: zope.browserresource; extra == "test"
Requires-Dist: zope.configuration; extra == "test"
Requires-Dist: zope.testing; extra == "test"
Requires-Dist: zope.testrunner>=6.4; extra == "test"
Provides-Extra: browser
Requires-Dist: zope.browsermenu; extra == "browser"
Requires-Dist: zope.browserpage; extra == "browser"
Requires-Dist: zope.browserresource; extra == "browser"
Dynamic: author
Dynamic: author-email
Dynamic: classifier
Dynamic: description
Dynamic: home-page
Dynamic: keywords
Dynamic: license
Dynamic: license-file
Dynamic: provides-extra
Dynamic: requires-dist
Dynamic: requires-python
Dynamic: summary
